src/__init__.py
src/buffer.py
src/command_line.py
src/common_definitions.py
src/model.py
src/utils.py
ddpg_tf2-1.0.1.dist-info/LICENSE
ddpg_tf2-1.0.1.dist-info/METADATA
ddpg_tf2-1.0.1.dist-info/WHEEL
ddpg_tf2-1.0.1.dist-info/entry_points.txt
ddpg_tf2-1.0.1.dist-info/top_level.txt
ddpg_tf2-1.0.1.dist-info/RECORD
