Metadata-Version: 2.1
Name: ddpg-tf2
Version: 1.0.1
Summary: Simple yet effective DDPG implementation for continuous action space,
Author: Samuel Matthew Koesnadi
Author-email: samuelmat19@gmail.com
License-File: LICENSE
Requires-Dist: tensorflow-gpu (==2.7.2)
Requires-Dist: tqdm (==4.37.0)
Requires-Dist: gym (==0.17.2)
Requires-Dist: box2d-py (==2.3.8)
Requires-Dist: matplotlib (==3.1.1)
Requires-Dist: pytest (==7.1.2)
Requires-Dist: bandit (==1.7.4)
Requires-Dist: pylint (==2.14.4)
